{
   "num_mip_levels" : 4,
   "padding" : 8,
   "resource_pack_name" : "vanilla",
   "texture_data" : {
      "cave_block" : {
         "textures" : "textures/blocks/cave_block"
      },
      "drawer_side" : {
         "textures" : "textures/blocks/drawer_side"
      },
      "drawer_side2" : {
         "textures" : "textures/blocks/drawer_side2"
      },
      "drawer_top_bottom" : {
         "textures" : "textures/blocks/drawer_top_bottom"
      },
      "elevator_block_side" : {
         "textures" : "textures/blocks/elevator_block_side"
      },
      "elevator_block_top" : {
         "textures" : "textures/blocks/elevator_block_top"
      },
      "fertilized_dirt" : {
         "textures" : "textures/blocks/fertilized_dirt"
      },
      "histerite_block" : {
         "textures" : "textures/blocks/histerite_block"
      },
      "histerite_ore" : {
         "textures" : "textures/blocks/histerite_ore"
      },
      "lucky_block" : {
         "textures" : "textures/blocks/lucky_block"
      },
      "neon_block" : {
         "textures" : "textures/blocks/neon_block"
      },
      "nocturite_block" : {
         "textures" : "textures/blocks/nocturite_block"
      },
      "nocturite_plant0" : {
         "textures" : "textures/blocks/nocturite_plant0"
      },
      "nocturite_plant1" : {
         "textures" : "textures/blocks/nocturite_plant1"
      },
      "nocturite_plant2" : {
         "textures" : "textures/blocks/nocturite_plant2"
      },
      "poisonous_obsidian" : {
         "textures" : "textures/blocks/poisonous_obsidian"
      },
      "renforced_obsidian" : {
         "textures" : "textures/blocks/renforced_obsidian"
      }
   },
   "texture_name" : "atlas.terrain"
}
